funcsigs/__init__.py
funcsigs/version.py
funcsigs-1.0.1.dist-info/DESCRIPTION.rst
funcsigs-1.0.1.dist-info/METADATA
funcsigs-1.0.1.dist-info/RECORD
funcsigs-1.0.1.dist-info/WHEEL
funcsigs-1.0.1.dist-info/metadata.json
funcsigs-1.0.1.dist-info/pbr.json
funcsigs-1.0.1.dist-info/top_level.txt
